{
	"start":	{
		"connected":	[{
				"socket":	329,
				"local_host":	"100.124.11.206",
				"local_port":	42251,
				"remote_host":	"168.61.1.168",
				"remote_port":	5201
			}],
		"version":	"iperf 3.7",
		"system_info":	"Linux localhost 4.19.110-g9ceb3bf92e0a-ab6790968 #2 SMP PREEMPT Wed Aug 26 04:14:37 UTC 2020 aarch64",
		"timestamp":	{
			"time":	"2021-01-23 12:17:02 CST",
			"timesecs":	1611425822
		},
		"connecting_to":	{
			"host":	"168.61.1.168",
			"port":	5201
		},
		"cookie":	"gteyvvgxdb7xngswspwropnt2tylim6rmoes",
		"sock_bufsize":	0,
		"sndbuf_actual":	212992,
		"rcvbuf_actual":	212992,
		"test_start":	{
			"protocol":	"UDP",
			"num_streams":	1,
			"blksize":	1376,
			"omit":	0,
			"duration":	30,
			"bytes":	0,
			"blocks":	0,
			"reverse":	1,
			"tos":	0
		}
	},
	"intervals":	[{
			"streams":	[{
					"socket":	329,
					"start":	0,
					"end":	1.038474,
					"seconds":	1.0384739637374878,
					"bytes":	1581024,
					"bits_per_second":	12179594.714612693,
					"jitter_ms":	0.010307596107106935,
					"lost_packets":	173369,
					"packets":	174518,
					"lost_percent":	99.341615191556173,
					"omitted":	false,
					"sender":	false
				}],
			"sum":	{
				"start":	0,
				"end":	1.038474,
				"seconds":	1.0384739637374878,
				"bytes":	1581024,
				"bits_per_second":	12179594.714612693,
				"jitter_ms":	0.010307596107106935,
				"lost_packets":	173369,
				"packets":	174518,
				"lost_percent":	99.341615191556173,
				"omitted":	false,
				"sender":	false
			}
		}, {
			"streams":	[{
					"socket":	329,
					"start":	1.038474,
					"end":	2.022092,
					"seconds":	0.98361802101135254,
					"bytes":	853120,
					"bits_per_second":	6938628.465735714,
					"jitter_ms":	0.050201356086335011,
					"lost_packets":	226864,
					"packets":	227484,
					"lost_percent":	99.727453359357142,
					"omitted":	false,
					"sender":	false
				}],
			"sum":	{
				"start":	1.038474,
				"end":	2.022092,
				"seconds":	0.98361802101135254,
				"bytes":	853120,
				"bits_per_second":	6938628.465735714,
				"jitter_ms":	0.050201356086335011,
				"lost_packets":	226864,
				"packets":	227484,
				"lost_percent":	99.727453359357142,
				"omitted":	false,
				"sender":	false
			}
		}, {
			"streams":	[{
					"socket":	329,
					"start":	2.022092,
					"end":	3.015924,
					"seconds":	0.993831992149353,
					"bytes":	1647072,
					"bits_per_second":	13258353.629272003,
					"jitter_ms":	0.012533292052911123,
					"lost_packets":	227043,
					"packets":	228240,
					"lost_percent":	99.475552050473183,
					"omitted":	false,
					"sender":	false
				}],
			"sum":	{
				"start":	2.022092,
				"end":	3.015924,
				"seconds":	0.993831992149353,
				"bytes":	1647072,
				"bits_per_second":	13258353.629272003,
				"jitter_ms":	0.012533292052911123,
				"lost_packets":	227043,
				"packets":	228240,
				"lost_percent":	99.475552050473183,
				"omitted":	false,
				"sender":	false
			}
		}, {
			"streams":	[{
					"socket":	329,
					"start":	3.015924,
					"end":	4.001275,
					"seconds":	0.985351026058197,
					"bytes":	1172352,
					"bits_per_second":	9518248.575351933,
					"jitter_ms":	0.009495669456329462,
					"lost_packets":	227123,
					"packets":	227975,
					"lost_percent":	99.626274810834516,
					"omitted":	false,
					"sender":	false
				}],
			"sum":	{
				"start":	3.015924,
				"end":	4.001275,
				"seconds":	0.985351026058197,
				"bytes":	1172352,
				"bits_per_second":	9518248.575351933,
				"jitter_ms":	0.009495669456329462,
				"lost_packets":	227123,
				"packets":	227975,
				"lost_percent":	99.626274810834516,
				"omitted":	false,
				"sender":	false
			}
		}, {
			"streams":	[{
					"socket":	329,
					"start":	4.001275,
					"end":	5.038477,
					"seconds":	1.037202000617981,
					"bytes":	733408,
					"bits_per_second":	5656819.0154899368,
					"jitter_ms":	0.32320603818066879,
					"lost_packets":	226383,
					"packets":	226916,
					"lost_percent":	99.765111318725872,
					"omitted":	false,
					"sender":	false
				}],
			"sum":	{
				"start":	4.001275,
				"end":	5.038477,
				"seconds":	1.037202000617981,
				"bytes":	733408,
				"bits_per_second":	5656819.0154899368,
				"jitter_ms":	0.32320603818066879,
				"lost_packets":	226383,
				"packets":	226916,
				"lost_percent":	99.765111318725872,
				"omitted":	false,
				"sender":	false
			}
		}, {
			"streams":	[{
					"socket":	329,
					"start":	5.038477,
					"end":	6.005504,
					"seconds":	0.96702700853347778,
					"bytes":	972832,
					"bits_per_second":	8048023.4071255205,
					"jitter_ms":	0.033279797393522444,
					"lost_packets":	221816,
					"packets":	222523,
					"lost_percent":	99.68228003397401,
					"omitted":	false,
					"sender":	false
				}],
			"sum":	{
				"start":	5.038477,
				"end":	6.005504,
				"seconds":	0.96702700853347778,
				"bytes":	972832,
				"bits_per_second":	8048023.4071255205,
				"jitter_ms":	0.033279797393522444,
				"lost_packets":	221816,
				"packets":	222523,
				"lost_percent":	99.68228003397401,
				"omitted":	false,
				"sender":	false
			}
		}, {
			"streams":	[{
					"socket":	329,
					"start":	6.005504,
					"end":	7.038456,
					"seconds":	1.0329519510269165,
					"bytes":	657728,
					"bits_per_second":	5093967.82180325,
					"jitter_ms":	0.016075735091889306,
					"lost_packets":	224643,
					"packets":	225121,
					"lost_percent":	99.787669742049829,
					"omitted":	false,
					"sender":	false
				}],
			"sum":	{
				"start":	6.005504,
				"end":	7.038456,
				"seconds":	1.0329519510269165,
				"bytes":	657728,
				"bits_per_second":	5093967.82180325,
				"jitter_ms":	0.016075735091889306,
				"lost_packets":	224643,
				"packets":	225121,
				"lost_percent":	99.787669742049829,
				"omitted":	false,
				"sender":	false
			}
		}, {
			"streams":	[{
					"socket":	329,
					"start":	7.038456,
					"end":	8.013936,
					"seconds":	0.97548002004623413,
					"bytes":	579296,
					"bits_per_second":	4750858.9666248094,
					"jitter_ms":	0.021818727642555782,
					"lost_packets":	229105,
					"packets":	229526,
					"lost_percent":	99.816578513980986,
					"omitted":	false,
					"sender":	false
				}],
			"sum":	{
				"start":	7.038456,
				"end":	8.013936,
				"seconds":	0.97548002004623413,
				"bytes":	579296,
				"bits_per_second":	4750858.9666248094,
				"jitter_ms":	0.021818727642555782,
				"lost_packets":	229105,
				"packets":	229526,
				"lost_percent":	99.816578513980986,
				"omitted":	false,
				"sender":	false
			}
		}, {
			"streams":	[{
					"socket":	329,
					"start":	8.013936,
					"end":	9.004713,
					"seconds":	0.99077701568603516,
					"bytes":	895776,
					"bits_per_second":	7232917.0807802444,
					"jitter_ms":	0.099691421494532736,
					"lost_packets":	236666,
					"packets":	237317,
					"lost_percent":	99.725683368658792,
					"omitted":	false,
					"sender":	false
				}],
			"sum":	{
				"start":	8.013936,
				"end":	9.004713,
				"seconds":	0.99077701568603516,
				"bytes":	895776,
				"bits_per_second":	7232917.0807802444,
				"jitter_ms":	0.099691421494532736,
				"lost_packets":	236666,
				"packets":	237317,
				"lost_percent":	99.725683368658792,
				"omitted":	false,
				"sender":	false
			}
		}, {
			"streams":	[{
					"socket":	329,
					"start":	9.004713,
					"end":	10.025191,
					"seconds":	1.0204780101776123,
					"bytes":	937056,
					"bits_per_second":	7346016.2053812966,
					"jitter_ms":	0.033307984805658962,
					"lost_packets":	223640,
					"packets":	224321,
					"lost_percent":	99.696417187869173,
					"omitted":	false,
					"sender":	false
				}],
			"sum":	{
				"start":	9.004713,
				"end":	10.025191,
				"seconds":	1.0204780101776123,
				"bytes":	937056,
				"bits_per_second":	7346016.2053812966,
				"jitter_ms":	0.033307984805658962,
				"lost_packets":	223640,
				"packets":	224321,
				"lost_percent":	99.696417187869173,
				"omitted":	false,
				"sender":	false
			}
		}, {
			"streams":	[{
					"socket":	329,
					"start":	10.025191,
					"end":	11.009468,
					"seconds":	0.98427700996398926,
					"bytes":	832480,
					"bits_per_second":	6766225.2928610584,
					"jitter_ms":	0.052697198240681753,
					"lost_packets":	230697,
					"packets":	231302,
					"lost_percent":	99.738437194663248,
					"omitted":	false,
					"sender":	false
				}],
			"sum":	{
				"start":	10.025191,
				"end":	11.009468,
				"seconds":	0.98427700996398926,
				"bytes":	832480,
				"bits_per_second":	6766225.2928610584,
				"jitter_ms":	0.052697198240681753,
				"lost_packets":	230697,
				"packets":	231302,
				"lost_percent":	99.738437194663248,
				"omitted":	false,
				"sender":	false
			}
		}, {
			"streams":	[{
					"socket":	329,
					"start":	11.009468,
					"end":	12.004345,
					"seconds":	0.99487698078155518,
					"bytes":	276576,
					"bits_per_second":	2224001.6029537842,
					"jitter_ms":	0.028144804523822595,
					"lost_packets":	233657,
					"packets":	233858,
					"lost_percent":	99.914050406657026,
					"omitted":	false,
					"sender":	false
				}],
			"sum":	{
				"start":	11.009468,
				"end":	12.004345,
				"seconds":	0.99487698078155518,
				"bytes":	276576,
				"bits_per_second":	2224001.6029537842,
				"jitter_ms":	0.028144804523822595,
				"lost_packets":	233657,
				"packets":	233858,
				"lost_percent":	99.914050406657026,
				"omitted":	false,
				"sender":	false
			}
		}, {
			"streams":	[{
					"socket":	329,
					"start":	12.004345,
					"end":	13.038552,
					"seconds":	1.0342069864273071,
					"bytes":	649472,
					"bits_per_second":	5023922.74292106,
					"jitter_ms":	0.026159081546315511,
					"lost_packets":	234303,
					"packets":	234775,
					"lost_percent":	99.798956447662661,
					"omitted":	false,
					"sender":	false
				}],
			"sum":	{
				"start":	12.004345,
				"end":	13.038552,
				"seconds":	1.0342069864273071,
				"bytes":	649472,
				"bits_per_second":	5023922.74292106,
				"jitter_ms":	0.026159081546315511,
				"lost_packets":	234303,
				"packets":	234775,
				"lost_percent":	99.798956447662661,
				"omitted":	false,
				"sender":	false
			}
		}, {
			"streams":	[{
					"socket":	329,
					"start":	13.038552,
					"end":	14.032978,
					"seconds":	0.99442601203918457,
					"bytes":	1023744,
					"bits_per_second":	8235858.5765526835,
					"jitter_ms":	0.022551640937669787,
					"lost_packets":	231333,
					"packets":	232077,
					"lost_percent":	99.679416745304366,
					"omitted":	false,
					"sender":	false
				}],
			"sum":	{
				"start":	13.038552,
				"end":	14.032978,
				"seconds":	0.99442601203918457,
				"bytes":	1023744,
				"bits_per_second":	8235858.5765526835,
				"jitter_ms":	0.022551640937669787,
				"lost_packets":	231333,
				"packets":	232077,
				"lost_percent":	99.679416745304366,
				"omitted":	false,
				"sender":	false
			}
		}, {
			"streams":	[{
					"socket":	329,
					"start":	14.032978,
					"end":	15.020391,
					"seconds":	0.98741298913955688,
					"bytes":	730656,
					"bits_per_second":	5919760.0844744984,
					"jitter_ms":	0.0324983874145344,
					"lost_packets":	235747,
					"packets":	236278,
					"lost_percent":	99.775264730529287,
					"omitted":	false,
					"sender":	false
				}],
			"sum":	{
				"start":	14.032978,
				"end":	15.020391,
				"seconds":	0.98741298913955688,
				"bytes":	730656,
				"bits_per_second":	5919760.0844744984,
				"jitter_ms":	0.0324983874145344,
				"lost_packets":	235747,
				"packets":	236278,
				"lost_percent":	99.775264730529287,
				"omitted":	false,
				"sender":	false
			}
		}, {
			"streams":	[{
					"socket":	329,
					"start":	15.020391,
					"end":	16.038554,
					"seconds":	1.0181629657745361,
					"bytes":	1065024,
					"bits_per_second":	8368200.6578568947,
					"jitter_ms":	0.024480646871700668,
					"lost_packets":	239115,
					"packets":	239889,
					"lost_percent":	99.677350774733313,
					"omitted":	false,
					"sender":	false
				}],
			"sum":	{
				"start":	15.020391,
				"end":	16.038554,
				"seconds":	1.0181629657745361,
				"bytes":	1065024,
				"bits_per_second":	8368200.6578568947,
				"jitter_ms":	0.024480646871700668,
				"lost_packets":	239115,
				"packets":	239889,
				"lost_percent":	99.677350774733313,
				"omitted":	false,
				"sender":	false
			}
		}, {
			"streams":	[{
					"socket":	329,
					"start":	16.038554,
					"end":	17.010581,
					"seconds":	0.9720270037651062,
					"bytes":	378400,
					"bits_per_second":	3114316.7713183551,
					"jitter_ms":	0.021750910657077082,
					"lost_packets":	233488,
					"packets":	233763,
					"lost_percent":	99.882359483750633,
					"omitted":	false,
					"sender":	false
				}],
			"sum":	{
				"start":	16.038554,
				"end":	17.010581,
				"seconds":	0.9720270037651062,
				"bytes":	378400,
				"bits_per_second":	3114316.7713183551,
				"jitter_ms":	0.021750910657077082,
				"lost_packets":	233488,
				"packets":	233763,
				"lost_percent":	99.882359483750633,
				"omitted":	false,
				"sender":	false
			}
		}, {
			"streams":	[{
					"socket":	329,
					"start":	17.010581,
					"end":	18.032522,
					"seconds":	1.0219409465789795,
					"bytes":	1297568,
					"bits_per_second":	10157674.995555872,
					"jitter_ms":	0.030198728326038763,
					"lost_packets":	234280,
					"packets":	235223,
					"lost_percent":	99.59910382913236,
					"omitted":	false,
					"sender":	false
				}],
			"sum":	{
				"start":	17.010581,
				"end":	18.032522,
				"seconds":	1.0219409465789795,
				"bytes":	1297568,
				"bits_per_second":	10157674.995555872,
				"jitter_ms":	0.030198728326038763,
				"lost_packets":	234280,
				"packets":	235223,
				"lost_percent":	99.59910382913236,
				"omitted":	false,
				"sender":	false
			}
		}, {
			"streams":	[{
					"socket":	329,
					"start":	18.032522,
					"end":	19.017105,
					"seconds":	0.98458302021026611,
					"bytes":	626080,
					"bits_per_second":	5087067.21240263,
					"jitter_ms":	0.012118903486100832,
					"lost_packets":	234427,
					"packets":	234882,
					"lost_percent":	99.806285709420052,
					"omitted":	false,
					"sender":	false
				}],
			"sum":	{
				"start":	18.032522,
				"end":	19.017105,
				"seconds":	0.98458302021026611,
				"bytes":	626080,
				"bits_per_second":	5087067.21240263,
				"jitter_ms":	0.012118903486100832,
				"lost_packets":	234427,
				"packets":	234882,
				"lost_percent":	99.806285709420052,
				"omitted":	false,
				"sender":	false
			}
		}, {
			"streams":	[{
					"socket":	329,
					"start":	19.017105,
					"end":	20.040111,
					"seconds":	1.0230059623718262,
					"bytes":	917792,
					"bits_per_second":	7177217.21091135,
					"jitter_ms":	0.013880341527911249,
					"lost_packets":	224240,
					"packets":	224907,
					"lost_percent":	99.70343297451835,
					"omitted":	false,
					"sender":	false
				}],
			"sum":	{
				"start":	19.017105,
				"end":	20.040111,
				"seconds":	1.0230059623718262,
				"bytes":	917792,
				"bits_per_second":	7177217.21091135,
				"jitter_ms":	0.013880341527911249,
				"lost_packets":	224240,
				"packets":	224907,
				"lost_percent":	99.70343297451835,
				"omitted":	false,
				"sender":	false
			}
		}, {
			"streams":	[{
					"socket":	329,
					"start":	20.040111,
					"end":	21.006498,
					"seconds":	0.96638697385787964,
					"bytes":	482976,
					"bits_per_second":	3998199.5872475673,
					"jitter_ms":	0.027367265185438625,
					"lost_packets":	239868,
					"packets":	240219,
					"lost_percent":	99.85388333146004,
					"omitted":	false,
					"sender":	false
				}],
			"sum":	{
				"start":	20.040111,
				"end":	21.006498,
				"seconds":	0.96638697385787964,
				"bytes":	482976,
				"bits_per_second":	3998199.5872475673,
				"jitter_ms":	0.027367265185438625,
				"lost_packets":	239868,
				"packets":	240219,
				"lost_percent":	99.85388333146004,
				"omitted":	false,
				"sender":	false
			}
		}, {
			"streams":	[{
					"socket":	329,
					"start":	21.006498,
					"end":	22.000205,
					"seconds":	0.993707001209259,
					"bytes":	1054016,
					"bits_per_second":	8485527.41375355,
					"jitter_ms":	0.027826331303968322,
					"lost_packets":	238232,
					"packets":	238998,
					"lost_percent":	99.679495225901476,
					"omitted":	false,
					"sender":	false
				}],
			"sum":	{
				"start":	21.006498,
				"end":	22.000205,
				"seconds":	0.993707001209259,
				"bytes":	1054016,
				"bits_per_second":	8485527.41375355,
				"jitter_ms":	0.027826331303968322,
				"lost_packets":	238232,
				"packets":	238998,
				"lost_percent":	99.679495225901476,
				"omitted":	false,
				"sender":	false
			}
		}, {
			"streams":	[{
					"socket":	329,
					"start":	22.000205,
					"end":	23.038504,
					"seconds":	1.0382989645004272,
					"bytes":	781568,
					"bits_per_second":	6021911.042749024,
					"jitter_ms":	0.014874592183477647,
					"lost_packets":	233230,
					"packets":	233798,
					"lost_percent":	99.757055235716308,
					"omitted":	false,
					"sender":	false
				}],
			"sum":	{
				"start":	22.000205,
				"end":	23.038504,
				"seconds":	1.0382989645004272,
				"bytes":	781568,
				"bits_per_second":	6021911.042749024,
				"jitter_ms":	0.014874592183477647,
				"lost_packets":	233230,
				"packets":	233798,
				"lost_percent":	99.757055235716308,
				"omitted":	false,
				"sender":	false
			}
		}, {
			"streams":	[{
					"socket":	329,
					"start":	23.038504,
					"end":	24.006983,
					"seconds":	0.9684789776802063,
					"bytes":	898528,
					"bits_per_second":	7422178.6591774281,
					"jitter_ms":	0.027397586586688848,
					"lost_packets":	227617,
					"packets":	228270,
					"lost_percent":	99.713935252113728,
					"omitted":	false,
					"sender":	false
				}],
			"sum":	{
				"start":	23.038504,
				"end":	24.006983,
				"seconds":	0.9684789776802063,
				"bytes":	898528,
				"bits_per_second":	7422178.6591774281,
				"jitter_ms":	0.027397586586688848,
				"lost_packets":	227617,
				"packets":	228270,
				"lost_percent":	99.713935252113728,
				"omitted":	false,
				"sender":	false
			}
		}, {
			"streams":	[{
					"socket":	329,
					"start":	24.006983,
					"end":	25.000161,
					"seconds":	0.99317800998687744,
					"bytes":	688000,
					"bits_per_second":	5541806.1461839275,
					"jitter_ms":	0.0622690219466197,
					"lost_packets":	225336,
					"packets":	225836,
					"lost_percent":	99.778600400290472,
					"omitted":	false,
					"sender":	false
				}],
			"sum":	{
				"start":	24.006983,
				"end":	25.000161,
				"seconds":	0.99317800998687744,
				"bytes":	688000,
				"bits_per_second":	5541806.1461839275,
				"jitter_ms":	0.0622690219466197,
				"lost_packets":	225336,
				"packets":	225836,
				"lost_percent":	99.778600400290472,
				"omitted":	false,
				"sender":	false
			}
		}, {
			"streams":	[{
					"socket":	329,
					"start":	25.000161,
					"end":	26.008718,
					"seconds":	1.0085569620132446,
					"bytes":	1150336,
					"bits_per_second":	9124609.0668294337,
					"jitter_ms":	0.030124631402097056,
					"lost_packets":	227231,
					"packets":	228067,
					"lost_percent":	99.6334410502177,
					"omitted":	false,
					"sender":	false
				}],
			"sum":	{
				"start":	25.000161,
				"end":	26.008718,
				"seconds":	1.0085569620132446,
				"bytes":	1150336,
				"bits_per_second":	9124609.0668294337,
				"jitter_ms":	0.030124631402097056,
				"lost_packets":	227231,
				"packets":	228067,
				"lost_percent":	99.6334410502177,
				"omitted":	false,
				"sender":	false
			}
		}, {
			"streams":	[{
					"socket":	329,
					"start":	26.008718,
					"end":	27.035442,
					"seconds":	1.0267239809036255,
					"bytes":	626080,
					"bits_per_second":	4878273.1222386258,
					"jitter_ms":	0.070493180647806269,
					"lost_packets":	232741,
					"packets":	233196,
					"lost_percent":	99.804885160980461,
					"omitted":	false,
					"sender":	false
				}],
			"sum":	{
				"start":	26.008718,
				"end":	27.035442,
				"seconds":	1.0267239809036255,
				"bytes":	626080,
				"bits_per_second":	4878273.1222386258,
				"jitter_ms":	0.070493180647806269,
				"lost_packets":	232741,
				"packets":	233196,
				"lost_percent":	99.804885160980461,
				"omitted":	false,
				"sender":	false
			}
		}, {
			"streams":	[{
					"socket":	329,
					"start":	27.035442,
					"end":	28.002196,
					"seconds":	0.96675401926040649,
					"bytes":	612320,
					"bits_per_second":	5067017.9822448874,
					"jitter_ms":	0.022861812117226391,
					"lost_packets":	234385,
					"packets":	234830,
					"lost_percent":	99.810501213643917,
					"omitted":	false,
					"sender":	false
				}],
			"sum":	{
				"start":	27.035442,
				"end":	28.002196,
				"seconds":	0.96675401926040649,
				"bytes":	612320,
				"bits_per_second":	5067017.9822448874,
				"jitter_ms":	0.022861812117226391,
				"lost_packets":	234385,
				"packets":	234830,
				"lost_percent":	99.810501213643917,
				"omitted":	false,
				"sender":	false
			}
		}, {
			"streams":	[{
					"socket":	329,
					"start":	28.002196,
					"end":	29.009539,
					"seconds":	1.007343053817749,
					"bytes":	447200,
					"bits_per_second":	3551520.9902338474,
					"jitter_ms":	0.051072663306727759,
					"lost_packets":	238784,
					"packets":	239109,
					"lost_percent":	99.864078725602127,
					"omitted":	false,
					"sender":	false
				}],
			"sum":	{
				"start":	28.002196,
				"end":	29.009539,
				"seconds":	1.007343053817749,
				"bytes":	447200,
				"bits_per_second":	3551520.9902338474,
				"jitter_ms":	0.051072663306727759,
				"lost_packets":	238784,
				"packets":	239109,
				"lost_percent":	99.864078725602127,
				"omitted":	false,
				"sender":	false
			}
		}, {
			"streams":	[{
					"socket":	329,
					"start":	29.009539,
					"end":	30.002236,
					"seconds":	0.99269700050354,
					"bytes":	879264,
					"bits_per_second":	7085860.0322474893,
					"jitter_ms":	0.088175431241807323,
					"lost_packets":	232690,
					"packets":	233329,
					"lost_percent":	99.726137771130041,
					"omitted":	false,
					"sender":	false
				}],
			"sum":	{
				"start":	29.009539,
				"end":	30.002236,
				"seconds":	0.99269700050354,
				"bytes":	879264,
				"bits_per_second":	7085860.0322474893,
				"jitter_ms":	0.088175431241807323,
				"lost_packets":	232690,
				"packets":	233329,
				"lost_percent":	99.726137771130041,
				"omitted":	false,
				"sender":	false
			}
		}],
	"end":	{
		"streams":	[{
				"udp":	{
					"socket":	329,
					"start":	0,
					"end":	30.156103,
					"seconds":	30.156103,
					"bytes":	9608189696,
					"bits_per_second":	2548920779.5848155,
					"jitter_ms":	0.088175431241807323,
					"lost_packets":	6878053,
					"packets":	6982696,
					"lost_percent":	98.5013954495513,
					"out_of_order":	0,
					"sender":	false
				}
			}],
		"sum":	{
			"start":	0,
			"end":	30.002236,
			"seconds":	30.002236,
			"bytes":	9608189696,
			"bits_per_second":	2548920779.5848155,
			"jitter_ms":	0.088175431241807323,
			"lost_packets":	6878053,
			"packets":	6982696,
			"lost_percent":	98.5013954495513,
			"sender":	false
		},
		"cpu_utilization_percent":	{
			"host_total":	51.113676875908176,
			"host_user":	37.103748743001994,
			"host_system":	14.009960915250264,
			"remote_total":	85.9382718545391,
			"remote_user":	17.125724163325071,
			"remote_system":	68.812547691214021
		}
	},
	"title":	"PXBMN-run60329-iPerf"
}
