{"start": {"connected": [{"socket": 362, "local_host": "100.124.11.206", "local_port": 39874, "remote_host": "52.247.225.34", "remote_port": 5201}], "version": "iperf 3.7", "system_info": "Linux localhost 4.19.110-g9ceb3bf92e0a-ab6790968 #2 SMP PREEMPT Wed Aug 26 04:14:37 UTC 2020 aarch64", "timestamp": {"time": "2021-01-23 12:27:00 CST", "timesecs": 1611426420}, "connecting_to": {"host": "52.247.225.34", "port": 5201}, "cookie": "ua7vhskrgj3u4hgmeaa6ecn5wnkfrfk3gerg", "tcp_mss_default": 1376, "target_bitrate": 3000000000, "sock_bufsize": 0, "sndbuf_actual": 2097152, "rcvbuf_actual": 6291456, "test_start": {"protocol": "TCP", "num_streams": 1, "blksize": 131072, "omit": 0, "duration": 30, "bytes": 0, "blocks": 0, "reverse": 1, "tos": 0}}, "intervals": [{"streams": [{"socket": 362, "start": 0, "end": 1.000974, "seconds": 1.0009740591049194, "bytes": 2560736, "bits_per_second": 20465952.95218607, "omitted": false, "sender": false}], "sum": {"start": 0, "end": 1.000974, "seconds": 1.0009740591049194, "bytes": 2560736, "bits_per_second": 20465952.95218607, "omitted": false, "sender": false}}, {"streams": [{"socket": 362, "start": 1.000974, "end": 2.003009, "seconds": 1.0020350217819214, "bytes": 5410784, "bits_per_second": 43198362.39158978, "omitted": false, "sender": false}], "sum": {"start": 1.000974, "end": 2.003009, "seconds": 1.0020350217819214, "bytes": 5410784, "bits_per_second": 43198362.39158978, "omitted": false, "sender": false}}, {"streams": [{"socket": 362, "start": 2.003009, "end": 3.005123, "seconds": 1.0021140575408936, "bytes": 10414592, "bits_per_second": 83140971.20287135, "omitted": false, "sender": false}], "sum": {"start": 2.003009, "end": 3.005123, "seconds": 1.0021140575408936, "bytes": 10414592, "bits_per_second": 83140971.20287135, "omitted": false, "sender": false}}, {"streams": [{"socket": 362, "start": 3.005123, "end": 4.000452, "seconds": 0.9953290224075317, "bytes": 17978816, "bits_per_second": 144505509.99919444, "omitted": false, "sender": false}], "sum": {"start": 3.005123, "end": 4.000452, "seconds": 0.9953290224075317, "bytes": 17978816, "bits_per_second": 144505509.99919444, "omitted": false, "sender": false}}, {"streams": [{"socket": 362, "start": 4.000452, "end": 5.000668, "seconds": 1.000216007232666, "bytes": 41547296, "bits_per_second": 332306587.37366474, "omitted": false, "sender": false}], "sum": {"start": 4.000452, "end": 5.000668, "seconds": 1.000216007232666, "bytes": 41547296, "bits_per_second": 332306587.37366474, "omitted": false, "sender": false}}, {"streams": [{"socket": 362, "start": 5.000668, "end": 6.000817, "seconds": 1.0001490116119385, "bytes": 97939552, "bits_per_second": 783399680.3508388, "omitted": false, "sender": false}], "sum": {"start": 5.000668, "end": 6.000817, "seconds": 1.0001490116119385, "bytes": 97939552, "bits_per_second": 783399680.3508388, "omitted": false, "sender": false}}, {"streams": [{"socket": 362, "start": 6.000817, "end": 7.003402, "seconds": 1.0025850534439087, "bytes": 130626432, "bits_per_second": 1042317010.8215312, "omitted": false, "sender": false}], "sum": {"start": 6.000817, "end": 7.003402, "seconds": 1.0025850534439087, "bytes": 130626432, "bits_per_second": 1042317010.8215312, "omitted": false, "sender": false}}, {"streams": [{"socket": 362, "start": 7.003402, "end": 8.000969, "seconds": 0.9975669980049133, "bytes": 130678720, "bits_per_second": 1047979496.2050769, "omitted": false, "sender": false}], "sum": {"start": 7.003402, "end": 8.000969, "seconds": 0.9975669980049133, "bytes": 130678720, "bits_per_second": 1047979496.2050769, "omitted": false, "sender": false}}, {"streams": [{"socket": 362, "start": 8.000969, "end": 9.00308, "seconds": 1.0021109580993652, "bytes": 131380128, "bits_per_second": 1048826994.1618412, "omitted": false, "sender": false}], "sum": {"start": 8.000969, "end": 9.00308, "seconds": 1.0021109580993652, "bytes": 131380128, "bits_per_second": 1048826994.1618412, "omitted": false, "sender": false}}, {"streams": [{"socket": 362, "start": 9.00308, "end": 10.000846, "seconds": 0.9977660179138184, "bytes": 129953920, "bits_per_second": 1041959077.9145956, "omitted": false, "sender": false}], "sum": {"start": 9.00308, "end": 10.000846, "seconds": 0.9977660179138184, "bytes": 129953920, "bits_per_second": 1041959077.9145956, "omitted": false, "sender": false}}, {"streams": [{"socket": 362, "start": 10.000846, "end": 11.000647, "seconds": 0.999800980091095, "bytes": 129042656, "bits_per_second": 1032546745.3592016, "omitted": false, "sender": false}], "sum": {"start": 10.000846, "end": 11.000647, "seconds": 0.999800980091095, "bytes": 129042656, "bits_per_second": 1032546745.3592016, "omitted": false, "sender": false}}, {"streams": [{"socket": 362, "start": 11.000647, "end": 12.000767, "seconds": 1.0001200437545776, "bytes": 129962848, "bits_per_second": 1039577989.1550056, "omitted": false, "sender": false}], "sum": {"start": 11.000647, "end": 12.000767, "seconds": 1.0001200437545776, "bytes": 129962848, "bits_per_second": 1039577989.1550056, "omitted": false, "sender": false}}, {"streams": [{"socket": 362, "start": 12.000767, "end": 13.000365, "seconds": 0.9995980262756348, "bytes": 128676992, "bits_per_second": 1029829900.560591, "omitted": false, "sender": false}], "sum": {"start": 12.000767, "end": 13.000365, "seconds": 0.9995980262756348, "bytes": 128676992, "bits_per_second": 1029829900.560591, "omitted": false, "sender": false}}, {"streams": [{"socket": 362, "start": 13.000365, "end": 14.000502, "seconds": 1.0001369714736938, "bytes": 129484352, "bits_per_second": 1035732950.1314672, "omitted": false, "sender": false}], "sum": {"start": 13.000365, "end": 14.000502, "seconds": 1.0001369714736938, "bytes": 129484352, "bits_per_second": 1035732950.1314672, "omitted": false, "sender": false}}, {"streams": [{"socket": 362, "start": 14.000502, "end": 15.001024, "seconds": 1.0005220174789429, "bytes": 129071552, "bits_per_second": 1032033676.3820709, "omitted": false, "sender": false}], "sum": {"start": 14.000502, "end": 15.001024, "seconds": 1.0005220174789429, "bytes": 129071552, "bits_per_second": 1032033676.3820709, "omitted": false, "sender": false}}, {"streams": [{"socket": 362, "start": 15.001024, "end": 16.001152, "seconds": 1.0001280307769775, "bytes": 108939296, "bits_per_second": 871402801.6222479, "omitted": false, "sender": false}], "sum": {"start": 15.001024, "end": 16.001152, "seconds": 1.0001280307769775, "bytes": 108939296, "bits_per_second": 871402801.6222479, "omitted": false, "sender": false}}, {"streams": [{"socket": 362, "start": 16.001152, "end": 17.001675, "seconds": 1.0005229711532593, "bytes": 99629280, "bits_per_second": 796617631.9583081, "omitted": false, "sender": false}], "sum": {"start": 16.001152, "end": 17.001675, "seconds": 1.0005229711532593, "bytes": 99629280, "bits_per_second": 796617631.9583081, "omitted": false, "sender": false}}, {"streams": [{"socket": 362, "start": 17.001675, "end": 18.004985, "seconds": 1.003309965133667, "bytes": 105013216, "bits_per_second": 837334181.0554788, "omitted": false, "sender": false}], "sum": {"start": 17.001675, "end": 18.004985, "seconds": 1.003309965133667, "bytes": 105013216, "bits_per_second": 837334181.0554788, "omitted": false, "sender": false}}, {"streams": [{"socket": 362, "start": 18.004985, "end": 19.017695, "seconds": 1.0127099752426147, "bytes": 109338336, "bits_per_second": 863728717.3856925, "omitted": false, "sender": false}], "sum": {"start": 18.004985, "end": 19.017695, "seconds": 1.0127099752426147, "bytes": 109338336, "bits_per_second": 863728717.3856925, "omitted": false, "sender": false}}, {"streams": [{"socket": 362, "start": 19.017695, "end": 20.000103, "seconds": 0.9824079871177673, "bytes": 116725792, "bits_per_second": 950528037.4802763, "omitted": false, "sender": false}], "sum": {"start": 19.017695, "end": 20.000103, "seconds": 0.9824079871177673, "bytes": 116725792, "bits_per_second": 950528037.4802763, "omitted": false, "sender": false}}, {"streams": [{"socket": 362, "start": 20.000103, "end": 21.001056, "seconds": 1.000952959060669, "bytes": 121235872, "bits_per_second": 968963593.3642452, "omitted": false, "sender": false}], "sum": {"start": 20.000103, "end": 21.001056, "seconds": 1.000952959060669, "bytes": 121235872, "bits_per_second": 968963593.3642452, "omitted": false, "sender": false}}, {"streams": [{"socket": 362, "start": 21.001056, "end": 22.001108, "seconds": 1.0000519752502441, "bytes": 123641856, "bits_per_second": 989083440.1406864, "omitted": false, "sender": false}], "sum": {"start": 21.001056, "end": 22.001108, "seconds": 1.0000519752502441, "bytes": 123641856, "bits_per_second": 989083440.1406864, "omitted": false, "sender": false}}, {"streams": [{"socket": 362, "start": 22.001108, "end": 23.000721, "seconds": 0.9996129870414734, "bytes": 123395552, "bits_per_second": 987546609.3349617, "omitted": false, "sender": false}], "sum": {"start": 22.001108, "end": 23.000721, "seconds": 0.9996129870414734, "bytes": 123395552, "bits_per_second": 987546609.3349617, "omitted": false, "sender": false}}, {"streams": [{"socket": 362, "start": 23.000721, "end": 24.001374, "seconds": 1.0006530284881592, "bytes": 127769856, "bits_per_second": 1021491784.7641284, "omitted": false, "sender": false}], "sum": {"start": 23.000721, "end": 24.001374, "seconds": 1.0006530284881592, "bytes": 127769856, "bits_per_second": 1021491784.7641284, "omitted": false, "sender": false}}, {"streams": [{"socket": 362, "start": 24.001374, "end": 25.001075, "seconds": 0.9997010231018066, "bytes": 127875808, "bits_per_second": 1023312410.7704549, "omitted": false, "sender": false}], "sum": {"start": 24.001374, "end": 25.001075, "seconds": 0.9997010231018066, "bytes": 127875808, "bits_per_second": 1023312410.7704549, "omitted": false, "sender": false}}, {"streams": [{"socket": 362, "start": 25.001075, "end": 26.001076, "seconds": 1.0000009536743164, "bytes": 132131776, "bits_per_second": 1057053199.9155122, "omitted": false, "sender": false}], "sum": {"start": 25.001075, "end": 26.001076, "seconds": 1.0000009536743164, "bytes": 132131776, "bits_per_second": 1057053199.9155122, "omitted": false, "sender": false}}, {"streams": [{"socket": 362, "start": 26.001076, "end": 27.000423, "seconds": 0.9993469715118408, "bytes": 121376960, "bits_per_second": 971650195.2580289, "omitted": false, "sender": false}], "sum": {"start": 26.001076, "end": 27.000423, "seconds": 0.9993469715118408, "bytes": 121376960, "bits_per_second": 971650195.2580289, "omitted": false, "sender": false}}, {"streams": [{"socket": 362, "start": 27.000423, "end": 28.000905, "seconds": 1.0004819631576538, "bytes": 125244896, "bits_per_second": 1001476493.2270082, "omitted": false, "sender": false}], "sum": {"start": 27.000423, "end": 28.000905, "seconds": 1.0004819631576538, "bytes": 125244896, "bits_per_second": 1001476493.2270082, "omitted": false, "sender": false}}, {"streams": [{"socket": 362, "start": 28.000905, "end": 29.000799, "seconds": 0.9998940229415894, "bytes": 130535616, "bits_per_second": 1044395609.974562, "omitted": false, "sender": false}], "sum": {"start": 28.000905, "end": 29.000799, "seconds": 0.9998940229415894, "bytes": 130535616, "bits_per_second": 1044395609.974562, "omitted": false, "sender": false}}, {"streams": [{"socket": 362, "start": 29.000799, "end": 30.001031, "seconds": 1.0002319812774658, "bytes": 79316768, "bits_per_second": 634386978.098413, "omitted": false, "sender": false}], "sum": {"start": 29.000799, "end": 30.001031, "seconds": 1.0002319812774658, "bytes": 79316768, "bits_per_second": 634386978.098413, "omitted": false, "sender": false}}], "end": {"streams": [{"sender": {"socket": 362, "start": 0, "end": 30.066846, "seconds": 30.066846, "bytes": 3115843584, "bits_per_second": 829044345.7887136, "retransmits": 2, "max_snd_cwnd": 0, "max_rtt": 0, "min_rtt": 0, "mean_rtt": 0, "sender": false}, "receiver": {"socket": 362, "start": 0, "end": 30.001031, "seconds": 30.001031, "bytes": 3096900256, "bits_per_second": 825811687.8716601, "sender": false}}], "sum_sent": {"start": 0, "end": 30.066846, "seconds": 30.066846, "bytes": 3115843584, "bits_per_second": 829044345.7887136, "retransmits": 2, "sender": false}, "sum_received": {"start": 0, "end": 30.001031, "seconds": 30.001031, "bytes": 3096900256, "bits_per_second": 825811687.8716601, "sender": false}, "cpu_utilization_percent": {"host_total": 54.87236620673068, "host_user": 30.88251863756229, "host_system": 23.989877099217356, "remote_total": 5.317886859841208, "remote_user": 0.333133147381956, "remote_system": 4.984756653486942}, "sender_tcp_congestion": "cubic"}, "title": "PXBMN-run60345-iPerf"}