{"start": {"connected": [{"socket": 6, "local_host": "10.5.0.4", "local_port": 5201, "remote_host": "174.248.221.155", "remote_port": 6307}], "version": "iperf 3.1.3", "system_info": "Linux az-north-central 5.4.0-1047-azure #49~18.04.1-Ubuntu SMP Thu Apr 22 21:28:54 UTC 2020 x86_64", "timestamp": {"time": "Sun, 17 Jan 2021 23:59:55 ", "timesecs": 1608271195.0}, "accepted_connection": {"host": "174.248.221.155", "port": 6320}, "cookie": "fshqdtkaz7odoomnzokunln7i42g2ylimi3r", "tcp_mss_default": 1376, "test_start": {"protocol": "TCP", "num_streams": 1, "blksize": 131072, "omit": 0, "duration": 30, "bytes": 0, "blocks": 0, "reverse": 1}}, "intervals": [{"streams": [{"socket": 6, "start": 0, "end": 0.500111, "seconds": 0.500111, "bytes": 12058624, "bits_per_second": 192895121.524304, "retransmits": 0, "snd_cwnd": 100448, "rtt": 25919, "omitted": false}], "sum": {"start": 0, "end": 0.500111, "seconds": 0.500111, "bytes": 12058624, "bits_per_second": 192895121.524304, "retransmits": 0, "omitted": false}}, {"streams": [{"socket": 6, "start": 0.500111, "end": 1.000111, "seconds": 0.5, "bytes": 3145728, "bits_per_second": 50331648, "retransmits": 0, "snd_cwnd": 257312, "rtt": 24636, "omitted": false}], "sum": {"start": 0.500111, "end": 1.000111, "seconds": 0.5, "bytes": 3145728, "bits_per_second": 50331648, "retransmits": 0, "omitted": false}}, {"streams": [{"socket": 6, "start": 1.000111, "end": 1.500115, "seconds": 0.500004, "bytes": 6029312, "bits_per_second": 96468210.006339, "retransmits": 0, "snd_cwnd": 557280, "rtt": 26668, "omitted": false}], "sum": {"start": 1.000111, "end": 1.500115, "seconds": 0.500004, "bytes": 6029312, "bits_per_second": 96468210.006339, "retransmits": 0, "omitted": false}}, {"streams": [{"socket": 6, "start": 1.500115, "end": 2.000107, "seconds": 0.499992, "bytes": 16646144, "bits_per_second": 266342622.070007, "retransmits": 0, "snd_cwnd": 1392512, "rtt": 27304, "omitted": false}], "sum": {"start": 1.500115, "end": 2.000107, "seconds": 0.499992, "bytes": 16646144, "bits_per_second": 266342622.070007, "retransmits": 0, "omitted": false}}, {"streams": [{"socket": 6, "start": 2.000107, "end": 2.500068, "seconds": 0.499961, "bytes": 39321600, "bits_per_second": 629194503.801021, "retransmits": 0, "snd_cwnd": 3283136, "rtt": 26520, "omitted": false}], "sum": {"start": 2.000107, "end": 2.500068, "seconds": 0.499961, "bytes": 39321600, "bits_per_second": 629194503.801021, "retransmits": 0, "omitted": false}}, {"streams": [{"socket": 6, "start": 2.500068, "end": 3.000108, "seconds": 0.50004, "bytes": 102891520, "bits_per_second": 1646133000.0, "retransmits": 0, "snd_cwnd": 8088128, "rtt": 29952, "omitted": false}], "sum": {"start": 2.500068, "end": 3.000108, "seconds": 0.50004, "bytes": 102891520, "bits_per_second": 1646133000.0, "retransmits": 0, "omitted": false}}, {"streams": [{"socket": 6, "start": 3.000108, "end": 3.500118, "seconds": 0.50001, "bytes": 121634816, "bits_per_second": 1946118000.0, "retransmits": 0, "snd_cwnd": 8617888, "rtt": 31319, "omitted": false}], "sum": {"start": 3.000108, "end": 3.500118, "seconds": 0.50001, "bytes": 121634816, "bits_per_second": 1946118000.0, "retransmits": 0, "omitted": false}}, {"streams": [{"socket": 6, "start": 3.500118, "end": 4.000314, "seconds": 0.500196, "bytes": 127401984, "bits_per_second": 2037633000.0, "retransmits": 0, "snd_cwnd": 8617888, "rtt": 32576, "omitted": false}], "sum": {"start": 3.500118, "end": 4.000314, "seconds": 0.500196, "bytes": 127401984, "bits_per_second": 2037633000.0, "retransmits": 0, "omitted": false}}, {"streams": [{"socket": 6, "start": 4.000314, "end": 4.500125, "seconds": 0.499811, "bytes": 88473600, "bits_per_second": 1416112000.0, "retransmits": 0, "snd_cwnd": 8617888, "rtt": 61928, "omitted": false}], "sum": {"start": 4.000314, "end": 4.500125, "seconds": 0.499811, "bytes": 88473600, "bits_per_second": 1416112000.0, "retransmits": 0, "omitted": false}}, {"streams": [{"socket": 6, "start": 4.500125, "end": 5.000067, "seconds": 0.499942, "bytes": 120848384, "bits_per_second": 1933799000.0, "retransmits": 0, "snd_cwnd": 8617888, "rtt": 33517, "omitted": false}], "sum": {"start": 4.500125, "end": 5.000067, "seconds": 0.499942, "bytes": 120848384, "bits_per_second": 1933799000.0, "retransmits": 0, "omitted": false}}, {"streams": [{"socket": 6, "start": 5.000067, "end": 5.500066, "seconds": 0.499999, "bytes": 120061952, "bits_per_second": 1920995000.0, "retransmits": 0, "snd_cwnd": 8617888, "rtt": 32406, "omitted": false}], "sum": {"start": 5.000067, "end": 5.500066, "seconds": 0.499999, "bytes": 120061952, "bits_per_second": 1920995000.0, "retransmits": 0, "omitted": false}}, {"streams": [{"socket": 6, "start": 5.500066, "end": 6.000104, "seconds": 0.500038, "bytes": 127270912, "bits_per_second": 2036179000.0, "retransmits": 0, "snd_cwnd": 8617888, "rtt": 33028, "omitted": false}], "sum": {"start": 5.500066, "end": 6.000104, "seconds": 0.500038, "bytes": 127270912, "bits_per_second": 2036179000.0, "retransmits": 0, "omitted": false}}, {"streams": [{"socket": 6, "start": 6.000104, "end": 6.500115, "seconds": 0.500011, "bytes": 122552320, "bits_per_second": 1960794000.0, "retransmits": 0, "snd_cwnd": 8617888, "rtt": 33454, "omitted": false}], "sum": {"start": 6.000104, "end": 6.500115, "seconds": 0.500011, "bytes": 122552320, "bits_per_second": 1960794000.0, "retransmits": 0, "omitted": false}}, {"streams": [{"socket": 6, "start": 6.500115, "end": 7.000509, "seconds": 0.500394, "bytes": 123338752, "bits_per_second": 1971867000.0, "retransmits": 0, "snd_cwnd": 8617888, "rtt": 32916, "omitted": false}], "sum": {"start": 6.500115, "end": 7.000509, "seconds": 0.500394, "bytes": 123338752, "bits_per_second": 1971867000.0, "retransmits": 0, "omitted": false}}, {"streams": [{"socket": 6, "start": 7.000509, "end": 7.500145, "seconds": 0.499636, "bytes": 116523008, "bits_per_second": 1865726000.0, "retransmits": 0, "snd_cwnd": 8617888, "rtt": 34463, "omitted": false}], "sum": {"start": 7.000509, "end": 7.500145, "seconds": 0.499636, "bytes": 116523008, "bits_per_second": 1865726000.0, "retransmits": 0, "omitted": false}}, {"streams": [{"socket": 6, "start": 7.500145, "end": 8.00016, "seconds": 0.500015, "bytes": 117178368, "bits_per_second": 1874798000.0, "retransmits": 0, "snd_cwnd": 8617888, "rtt": 33073, "omitted": false}], "sum": {"start": 7.500145, "end": 8.00016, "seconds": 0.500015, "bytes": 117178368, "bits_per_second": 1874798000.0, "retransmits": 0, "omitted": false}}, {"streams": [{"socket": 6, "start": 8.00016, "end": 8.500113, "seconds": 0.499953, "bytes": 92536832, "bits_per_second": 1480729000.0, "retransmits": 0, "snd_cwnd": 8617888, "rtt": 33245, "omitted": false}], "sum": {"start": 8.00016, "end": 8.500113, "seconds": 0.499953, "bytes": 92536832, "bits_per_second": 1480729000.0, "retransmits": 0, "omitted": false}}, {"streams": [{"socket": 6, "start": 8.500113, "end": 9.000133, "seconds": 0.50002, "bytes": 127270912, "bits_per_second": 2036253000.0, "retransmits": 0, "snd_cwnd": 8617888, "rtt": 32928, "omitted": false}], "sum": {"start": 8.500113, "end": 9.000133, "seconds": 0.50002, "bytes": 127270912, "bits_per_second": 2036253000.0, "retransmits": 0, "omitted": false}}, {"streams": [{"socket": 6, "start": 9.000133, "end": 9.500081, "seconds": 0.499948, "bytes": 119013376, "bits_per_second": 1904412000.0, "retransmits": 0, "snd_cwnd": 8617888, "rtt": 35790, "omitted": false}], "sum": {"start": 9.000133, "end": 9.500081, "seconds": 0.499948, "bytes": 119013376, "bits_per_second": 1904412000.0, "retransmits": 0, "omitted": false}}, {"streams": [{"socket": 6, "start": 9.500081, "end": 10.000116, "seconds": 0.500035, "bytes": 125173760, "bits_per_second": 2002640000.0, "retransmits": 0, "snd_cwnd": 8617888, "rtt": 33265, "omitted": false}], "sum": {"start": 9.500081, "end": 10.000116, "seconds": 0.500035, "bytes": 125173760, "bits_per_second": 2002640000.0, "retransmits": 0, "omitted": false}}, {"streams": [{"socket": 6, "start": 10.000116, "end": 10.50004, "seconds": 0.499924, "bytes": 118751232, "bits_per_second": 1900309000.0, "retransmits": 0, "snd_cwnd": 8617888, "rtt": 33309, "omitted": false}], "sum": {"start": 10.000116, "end": 10.50004, "seconds": 0.499924, "bytes": 118751232, "bits_per_second": 1900309000.0, "retransmits": 0, "omitted": false}}, {"streams": [{"socket": 6, "start": 10.50004, "end": 11.000141, "seconds": 0.500101, "bytes": 126746624, "bits_per_second": 2027536000.0, "retransmits": 0, "snd_cwnd": 8617888, "rtt": 30286, "omitted": false}], "sum": {"start": 10.50004, "end": 11.000141, "seconds": 0.500101, "bytes": 126746624, "bits_per_second": 2027536000.0, "retransmits": 0, "omitted": false}}, {"streams": [{"socket": 6, "start": 11.000141, "end": 11.500044, "seconds": 0.499903, "bytes": 118095872, "bits_per_second": 1889901000.0, "retransmits": 0, "snd_cwnd": 8617888, "rtt": 35340, "omitted": false}], "sum": {"start": 11.000141, "end": 11.500044, "seconds": 0.499903, "bytes": 118095872, "bits_per_second": 1889901000.0, "retransmits": 0, "omitted": false}}, {"streams": [{"socket": 6, "start": 11.500044, "end": 12.000068, "seconds": 0.500024, "bytes": 126353408, "bits_per_second": 2021557000.0, "retransmits": 0, "snd_cwnd": 8617888, "rtt": 33254, "omitted": false}], "sum": {"start": 11.500044, "end": 12.000068, "seconds": 0.500024, "bytes": 126353408, "bits_per_second": 2021557000.0, "retransmits": 0, "omitted": false}}, {"streams": [{"socket": 6, "start": 12.000068, "end": 12.500174, "seconds": 0.500106, "bytes": 120717312, "bits_per_second": 1931068000.0, "retransmits": 0, "snd_cwnd": 8617888, "rtt": 33511, "omitted": false}], "sum": {"start": 12.000068, "end": 12.500174, "seconds": 0.500106, "bytes": 120717312, "bits_per_second": 1931068000.0, "retransmits": 0, "omitted": false}}, {"streams": [{"socket": 6, "start": 12.500174, "end": 13.000103, "seconds": 0.499929, "bytes": 124649472, "bits_per_second": 1994675000.0, "retransmits": 0, "snd_cwnd": 8617888, "rtt": 33174, "omitted": false}], "sum": {"start": 12.500174, "end": 13.000103, "seconds": 0.499929, "bytes": 124649472, "bits_per_second": 1994675000.0, "retransmits": 0, "omitted": false}}, {"streams": [{"socket": 6, "start": 13.000103, "end": 13.500115, "seconds": 0.500012, "bytes": 119668736, "bits_per_second": 1914653000.0, "retransmits": 0, "snd_cwnd": 8617888, "rtt": 32341, "omitted": false}], "sum": {"start": 13.000103, "end": 13.500115, "seconds": 0.500012, "bytes": 119668736, "bits_per_second": 1914653000.0, "retransmits": 0, "omitted": false}}, {"streams": [{"socket": 6, "start": 13.500115, "end": 14.000092, "seconds": 0.499977, "bytes": 123207680, "bits_per_second": 1971414000.0, "retransmits": 0, "snd_cwnd": 8617888, "rtt": 31882, "omitted": false}], "sum": {"start": 13.500115, "end": 14.000092, "seconds": 0.499977, "bytes": 123207680, "bits_per_second": 1971414000.0, "retransmits": 0, "omitted": false}}, {"streams": [{"socket": 6, "start": 14.000092, "end": 14.500089, "seconds": 0.499997, "bytes": 120193024, "bits_per_second": 1923099000.0, "retransmits": 0, "snd_cwnd": 8617888, "rtt": 32920, "omitted": false}], "sum": {"start": 14.000092, "end": 14.500089, "seconds": 0.499997, "bytes": 120193024, "bits_per_second": 1923099000.0, "retransmits": 0, "omitted": false}}, {"streams": [{"socket": 6, "start": 14.500089, "end": 15.000113, "seconds": 0.500024, "bytes": 125435904, "bits_per_second": 2006879000.0, "retransmits": 0, "snd_cwnd": 8617888, "rtt": 30512, "omitted": false}], "sum": {"start": 14.500089, "end": 15.000113, "seconds": 0.500024, "bytes": 125435904, "bits_per_second": 2006879000.0, "retransmits": 0, "omitted": false}}, {"streams": [{"socket": 6, "start": 15.000113, "end": 15.500056, "seconds": 0.499943, "bytes": 120061952, "bits_per_second": 1921210000.0, "retransmits": 0, "snd_cwnd": 8617888, "rtt": 34372, "omitted": false}], "sum": {"start": 15.000113, "end": 15.500056, "seconds": 0.499943, "bytes": 120061952, "bits_per_second": 1921210000.0, "retransmits": 0, "omitted": false}}, {"streams": [{"socket": 6, "start": 15.500056, "end": 16.000127, "seconds": 0.500071, "bytes": 125566976, "bits_per_second": 2008786000.0, "retransmits": 0, "snd_cwnd": 8617888, "rtt": 33290, "omitted": false}], "sum": {"start": 15.500056, "end": 16.000127, "seconds": 0.500071, "bytes": 125566976, "bits_per_second": 2008786000.0, "retransmits": 0, "omitted": false}}, {"streams": [{"socket": 6, "start": 16.000127, "end": 16.500118, "seconds": 0.499991, "bytes": 117440512, "bits_per_second": 1879082000.0, "retransmits": 0, "snd_cwnd": 8617888, "rtt": 32204, "omitted": false}], "sum": {"start": 16.000127, "end": 16.500118, "seconds": 0.499991, "bytes": 117440512, "bits_per_second": 1879082000.0, "retransmits": 0, "omitted": false}}, {"streams": [{"socket": 6, "start": 16.500118, "end": 17.000102, "seconds": 0.499984, "bytes": 121241600, "bits_per_second": 1939928000.0, "retransmits": 0, "snd_cwnd": 8617888, "rtt": 31406, "omitted": false}], "sum": {"start": 16.500118, "end": 17.000102, "seconds": 0.499984, "bytes": 121241600, "bits_per_second": 1939928000.0, "retransmits": 0, "omitted": false}}, {"streams": [{"socket": 6, "start": 17.000102, "end": 17.500119, "seconds": 0.500017, "bytes": 80609280, "bits_per_second": 1289704000.0, "retransmits": 0, "snd_cwnd": 8617888, "rtt": 91504, "omitted": false}], "sum": {"start": 17.000102, "end": 17.500119, "seconds": 0.500017, "bytes": 80609280, "bits_per_second": 1289704000.0, "retransmits": 0, "omitted": false}}, {"streams": [{"socket": 6, "start": 17.500119, "end": 18.000118, "seconds": 0.499999, "bytes": 85852160, "bits_per_second": 1373638000.0, "retransmits": 0, "snd_cwnd": 8617888, "rtt": 31403, "omitted": false}], "sum": {"start": 17.500119, "end": 18.000118, "seconds": 0.499999, "bytes": 85852160, "bits_per_second": 1373638000.0, "retransmits": 0, "omitted": false}}, {"streams": [{"socket": 6, "start": 18.000118, "end": 18.500046, "seconds": 0.499928, "bytes": 115343360, "bits_per_second": 1845760000.0, "retransmits": 0, "snd_cwnd": 8617888, "rtt": 35235, "omitted": false}], "sum": {"start": 18.000118, "end": 18.500046, "seconds": 0.499928, "bytes": 115343360, "bits_per_second": 1845760000.0, "retransmits": 0, "omitted": false}}, {"streams": [{"socket": 6, "start": 18.500046, "end": 19.00012, "seconds": 0.500074, "bytes": 127270912, "bits_per_second": 2036033000.0, "retransmits": 0, "snd_cwnd": 8617888, "rtt": 31227, "omitted": false}], "sum": {"start": 18.500046, "end": 19.00012, "seconds": 0.500074, "bytes": 127270912, "bits_per_second": 2036033000.0, "retransmits": 0, "omitted": false}}, {"streams": [{"socket": 6, "start": 19.00012, "end": 19.500139, "seconds": 0.500019, "bytes": 118358016, "bits_per_second": 1893657000.0, "retransmits": 0, "snd_cwnd": 8617888, "rtt": 31423, "omitted": false}], "sum": {"start": 19.00012, "end": 19.500139, "seconds": 0.500019, "bytes": 118358016, "bits_per_second": 1893657000.0, "retransmits": 0, "omitted": false}}, {"streams": [{"socket": 6, "start": 19.500139, "end": 20.000119, "seconds": 0.49998, "bytes": 120455168, "bits_per_second": 1927359000.0, "retransmits": 0, "snd_cwnd": 8617888, "rtt": 32564, "omitted": false}], "sum": {"start": 19.500139, "end": 20.000119, "seconds": 0.49998, "bytes": 120455168, "bits_per_second": 1927359000.0, "retransmits": 0, "omitted": false}}, {"streams": [{"socket": 6, "start": 20.000119, "end": 20.500109, "seconds": 0.49999, "bytes": 117047296, "bits_per_second": 1872794000.0, "retransmits": 0, "snd_cwnd": 8617888, "rtt": 33128, "omitted": false}], "sum": {"start": 20.000119, "end": 20.500109, "seconds": 0.49999, "bytes": 117047296, "bits_per_second": 1872794000.0, "retransmits": 0, "omitted": false}}, {"streams": [{"socket": 6, "start": 20.500109, "end": 21.000119, "seconds": 0.50001, "bytes": 125304832, "bits_per_second": 2004837000.0, "retransmits": 0, "snd_cwnd": 8617888, "rtt": 33295, "omitted": false}], "sum": {"start": 20.500109, "end": 21.000119, "seconds": 0.50001, "bytes": 125304832, "bits_per_second": 2004837000.0, "retransmits": 0, "omitted": false}}, {"streams": [{"socket": 6, "start": 21.000119, "end": 21.50011, "seconds": 0.499991, "bytes": 83886080, "bits_per_second": 1342202000.0, "retransmits": 0, "snd_cwnd": 8617888, "rtt": 41007, "omitted": false}], "sum": {"start": 21.000119, "end": 21.50011, "seconds": 0.499991, "bytes": 83886080, "bits_per_second": 1342202000.0, "retransmits": 0, "omitted": false}}, {"streams": [{"socket": 6, "start": 21.50011, "end": 22.000197, "seconds": 0.500087, "bytes": 127008768, "bits_per_second": 2031787000.0, "retransmits": 0, "snd_cwnd": 8617888, "rtt": 33680, "omitted": false}], "sum": {"start": 21.50011, "end": 22.000197, "seconds": 0.500087, "bytes": 127008768, "bits_per_second": 2031787000.0, "retransmits": 0, "omitted": false}}, {"streams": [{"socket": 6, "start": 22.000197, "end": 22.500076, "seconds": 0.499879, "bytes": 120586240, "bits_per_second": 1929847000.0, "retransmits": 0, "snd_cwnd": 8617888, "rtt": 39128, "omitted": false}], "sum": {"start": 22.000197, "end": 22.500076, "seconds": 0.499879, "bytes": 120586240, "bits_per_second": 1929847000.0, "retransmits": 0, "omitted": false}}, {"streams": [{"socket": 6, "start": 22.500076, "end": 23.000101, "seconds": 0.500025, "bytes": 123600896, "bits_per_second": 1977515000.0, "retransmits": 0, "snd_cwnd": 8617888, "rtt": 32915, "omitted": false}], "sum": {"start": 22.500076, "end": 23.000101, "seconds": 0.500025, "bytes": 123600896, "bits_per_second": 1977515000.0, "retransmits": 0, "omitted": false}}, {"streams": [{"socket": 6, "start": 23.000101, "end": 23.500118, "seconds": 0.500017, "bytes": 116391936, "bits_per_second": 1862208000.0, "retransmits": 0, "snd_cwnd": 8617888, "rtt": 41778, "omitted": false}], "sum": {"start": 23.000101, "end": 23.500118, "seconds": 0.500017, "bytes": 116391936, "bits_per_second": 1862208000.0, "retransmits": 0, "omitted": false}}, {"streams": [{"socket": 6, "start": 23.500118, "end": 24.000105, "seconds": 0.499987, "bytes": 121634816, "bits_per_second": 1946207000.0, "retransmits": 0, "snd_cwnd": 8617888, "rtt": 32823, "omitted": false}], "sum": {"start": 23.500118, "end": 24.000105, "seconds": 0.499987, "bytes": 121634816, "bits_per_second": 1946207000.0, "retransmits": 0, "omitted": false}}, {"streams": [{"socket": 6, "start": 24.000105, "end": 24.500068, "seconds": 0.499963, "bytes": 122421248, "bits_per_second": 1958885000.0, "retransmits": 0, "snd_cwnd": 8617888, "rtt": 43052, "omitted": false}], "sum": {"start": 24.000105, "end": 24.500068, "seconds": 0.499963, "bytes": 122421248, "bits_per_second": 1958885000.0, "retransmits": 0, "omitted": false}}, {"streams": [{"socket": 6, "start": 24.500068, "end": 25.000151, "seconds": 0.500083, "bytes": 124387328, "bits_per_second": 1989867000.0, "retransmits": 0, "snd_cwnd": 8617888, "rtt": 35311, "omitted": false}], "sum": {"start": 24.500068, "end": 25.000151, "seconds": 0.500083, "bytes": 124387328, "bits_per_second": 1989867000.0, "retransmits": 0, "omitted": false}}, {"streams": [{"socket": 6, "start": 25.000151, "end": 25.500104, "seconds": 0.499953, "bytes": 121372672, "bits_per_second": 1942145000.0, "retransmits": 0, "snd_cwnd": 8617888, "rtt": 42554, "omitted": false}], "sum": {"start": 25.000151, "end": 25.500104, "seconds": 0.499953, "bytes": 121372672, "bits_per_second": 1942145000.0, "retransmits": 0, "omitted": false}}, {"streams": [{"socket": 6, "start": 25.500104, "end": 26.000103, "seconds": 0.499999, "bytes": 125304832, "bits_per_second": 2004882000.0, "retransmits": 0, "snd_cwnd": 8617888, "rtt": 33103, "omitted": false}], "sum": {"start": 25.500104, "end": 26.000103, "seconds": 0.499999, "bytes": 125304832, "bits_per_second": 2004882000.0, "retransmits": 0, "omitted": false}}, {"streams": [{"socket": 6, "start": 26.000103, "end": 26.500107, "seconds": 0.500004, "bytes": 120586240, "bits_per_second": 1929364000.0, "retransmits": 0, "snd_cwnd": 8617888, "rtt": 35246, "omitted": false}], "sum": {"start": 26.000103, "end": 26.500107, "seconds": 0.500004, "bytes": 120586240, "bits_per_second": 1929364000.0, "retransmits": 0, "omitted": false}}, {"streams": [{"socket": 6, "start": 26.500107, "end": 27.000117, "seconds": 0.50001, "bytes": 122683392, "bits_per_second": 1962895000.0, "retransmits": 0, "snd_cwnd": 8617888, "rtt": 35512, "omitted": false}], "sum": {"start": 26.500107, "end": 27.000117, "seconds": 0.50001, "bytes": 122683392, "bits_per_second": 1962895000.0, "retransmits": 0, "omitted": false}}, {"streams": [{"socket": 6, "start": 27.000117, "end": 27.50013, "seconds": 0.500013, "bytes": 121634816, "bits_per_second": 1946106000.0, "retransmits": 0, "snd_cwnd": 8617888, "rtt": 33799, "omitted": false}], "sum": {"start": 27.000117, "end": 27.50013, "seconds": 0.500013, "bytes": 121634816, "bits_per_second": 1946106000.0, "retransmits": 0, "omitted": false}}, {"streams": [{"socket": 6, "start": 27.50013, "end": 28.000106, "seconds": 0.499976, "bytes": 120717312, "bits_per_second": 1931570000.0, "retransmits": 0, "snd_cwnd": 8617888, "rtt": 34388, "omitted": false}], "sum": {"start": 27.50013, "end": 28.000106, "seconds": 0.499976, "bytes": 120717312, "bits_per_second": 1931570000.0, "retransmits": 0, "omitted": false}}, {"streams": [{"socket": 6, "start": 28.000106, "end": 28.500072, "seconds": 0.499966, "bytes": 123207680, "bits_per_second": 1971457000.0, "retransmits": 0, "snd_cwnd": 8617888, "rtt": 32577, "omitted": false}], "sum": {"start": 28.000106, "end": 28.500072, "seconds": 0.499966, "bytes": 123207680, "bits_per_second": 1971457000.0, "retransmits": 0, "omitted": false}}, {"streams": [{"socket": 6, "start": 28.500072, "end": 29.000214, "seconds": 0.500142, "bytes": 122945536, "bits_per_second": 1966570000.0, "retransmits": 0, "snd_cwnd": 8617888, "rtt": 33322, "omitted": false}], "sum": {"start": 28.500072, "end": 29.000214, "seconds": 0.500142, "bytes": 122945536, "bits_per_second": 1966570000.0, "retransmits": 0, "omitted": false}}, {"streams": [{"socket": 6, "start": 29.000214, "end": 29.500129, "seconds": 0.499915, "bytes": 122552320, "bits_per_second": 1961170000.0, "retransmits": 0, "snd_cwnd": 8617888, "rtt": 42656, "omitted": false}], "sum": {"start": 29.000214, "end": 29.500129, "seconds": 0.499915, "bytes": 122552320, "bits_per_second": 1961170000.0, "retransmits": 0, "omitted": false}}, {"streams": [{"socket": 6, "start": 29.500129, "end": 30.000068, "seconds": 0.499939, "bytes": 123469824, "bits_per_second": 1975758000.0, "retransmits": 0, "snd_cwnd": 8617888, "rtt": 33726, "omitted": false}], "sum": {"start": 29.500129, "end": 30.000068, "seconds": 0.499939, "bytes": 123469824, "bits_per_second": 1975758000.0, "retransmits": 0, "omitted": false}}, {"streams": [{"socket": 6, "start": 30.000068, "end": 30.042368, "seconds": 0.0423, "bytes": 9437184, "bits_per_second": 1784811000.0, "retransmits": 0, "snd_cwnd": 8617888, "rtt": 33201, "omitted": false}], "sum": {"start": 30.000068, "end": 30.042368, "seconds": 0.0423, "bytes": 9437184, "bits_per_second": 1784811000.0, "retransmits": 0, "omitted": false}}], "end": {"streams": [{"sender": {"socket": 6, "start": 0, "end": 30.042368, "seconds": 30.042368, "bytes": 6601572352, "bits_per_second": 1757937000.0, "retransmits": 0, "max_snd_cwnd": 8617888, "max_rtt": 91504, "min_rtt": 24636, "mean_rtt": 34791}, "receiver": {"socket": 6, "start": 0, "end": 30.042368, "seconds": 30.042368, "bytes": 0, "bits_per_second": 0}}], "sum_sent": {"start": 0, "end": 30.042368, "seconds": 30.042368, "bytes": 6601572352, "bits_per_second": 1757937000.0, "retransmits": 0}, "sum_received": {"start": 0, "end": 30.042368, "seconds": 30.042368, "bytes": 0, "bits_per_second": 0}, "cpu_utilization_percent": {"host_total": 11.502772, "host_user": 0.262553, "host_system": 11.240219, "remote_total": 0, "remote_user": 0, "remote_system": 0}}, "title": "HUCKLEBERRY_830_cubic_1621295279_64529_30_1"}